scheduling_and_allocation/AllocationManager.py
scheduling_and_allocation/SchedulerProgram.py
scheduling_and_allocation/__init__.py
scheduling_and_allocation/allocation_ico.ico
scheduling_and_allocation/allocation_ico.png
scheduling_and_allocation/allocation_logo.png
scheduling_and_allocation/schedule_ico.ico
scheduling_and_allocation/schedule_ico.png
scheduling_and_allocation/schedule_logo.png
scheduling_and_allocation/to_do.txt
scheduling_and_allocation/Utilities/Colour.py
scheduling_and_allocation/Utilities/Preferences.py
scheduling_and_allocation/Utilities/__init__.py
scheduling_and_allocation/Utilities/id_generator.py
scheduling_and_allocation/ci_calculator/ci_calculation.py
scheduling_and_allocation/ci_calculator/ci_constants.py
scheduling_and_allocation/ci_calculator/personal_ci_calculator.py
scheduling_and_allocation/export/__init__.py
scheduling_and_allocation/export/registrars_office.py
scheduling_and_allocation/export/view_export_canvases.py
scheduling_and_allocation/export/view_template.tex
scheduling_and_allocation/gui_dialogs/__init__.py
scheduling_and_allocation/gui_dialogs/add_edit_block_dialog_tk.py
scheduling_and_allocation/gui_dialogs/add_section_dialog_tk.py
scheduling_and_allocation/gui_dialogs/change_font_tk.py
scheduling_and_allocation/gui_dialogs/dialog_utilities.py
scheduling_and_allocation/gui_dialogs/edit_course_dialog_tk.py
scheduling_and_allocation/gui_dialogs/edit_section_dialog_tk.py
scheduling_and_allocation/gui_generics/add_remove_tk.py
scheduling_and_allocation/gui_generics/block_colours.py
scheduling_and_allocation/gui_generics/drawing_scale.py
scheduling_and_allocation/gui_generics/menu_and_toolbars.py
scheduling_and_allocation/gui_generics/number_validations.py
scheduling_and_allocation/gui_generics/read_only_text_tk.py
scheduling_and_allocation/gui_pages/__init__.py
scheduling_and_allocation/gui_pages/allocation_grid_tk.py
scheduling_and_allocation/gui_pages/allocation_manager_tk.py
scheduling_and_allocation-2025.0.10.dist-info/METADATA
scheduling_and_allocation-2025.0.10.dist-info/WHEEL
scheduling_and_allocation-2025.0.10.dist-info/entry_points.txt
scheduling_and_allocation-2025.0.10.dist-info/licenses/LICENSE
scheduling_and_allocation-2025.0.10.dist-info/RECORD
