Metadata-Version: 2.4
Name: scheduling_and_allocation
Version: 2025.0.10
Summary: A visual tool to make scheduling courses with teachers, labs, etc easier
Project-URL: Issues, https://github.com/sandy-bultena/Scheduling_and_allocation/issues
Project-URL: Repository, https://github.com/sandy-bultena/Scheduling_and_allocation.git
Author: Ian Clement
Author-email: Sandy Bultena <sandy.bultena@gmail.com>
License-Expression: GPL-3.0-or-later
License-File: LICENSE
Classifier: Development Status :: 4 - Beta
Classifier: Intended Audience :: End Users/Desktop
Classifier: Operating System :: OS Independent
Classifier: Programming Language :: Python :: 3.12
Classifier: Programming Language :: Python :: 3.13
Requires-Python: >=3.11
Requires-Dist: pillow>=11.3.0
Requires-Dist: reportlab>=4.4.3
